Workbook

Sheet Project Explanation
A1: Investment Analysis Summary & Key Risks
A2: One-page recap of the analysis
A4: Deal Snapshot | D4: Other Key Assumptions
A5: Units | B5: =Assumptions!$B$7 -> 40 | D5: Annual Rent Growth | E5: =Assumptions!$B$17 -> 0.03
A6: Purchase Price | B6: =Assumptions!$B$10 -> 6000000 | D6: Annual Expense Growth | E6: =Assumptions!$B$18 -> 0.025
A7: Total Acquisition Cost | B7: =Assumptions!$B$13 -> 6220000 | D7: Vacancy & Credit Loss | E7: =Assumptions!$B$16 -> 0.05
A8: Going-In Cap Rate (Yr 1 NOI / Total Cost) | B8: ='Operating Expenses'!$B$21/B7 -> 0.078337235 | D8: Loan-to-Value (LTV) | E8: =Assumptions!$B$24 -> 0.7
A9: Hold Period | B9: =Assumptions!$B$32 -> 5 | D9: Interest Rate | E9: =Assumptions!$B$26 -> 0.065
A10: Assumed Exit Cap Rate | B10: =Assumptions!$B$33 -> 0.08 | D10: Amortization Period | E10: =Assumptions!$B$27 -> 30
A11: Initial Equity Investment | B11: ='Cash Flow & Returns'!$B$7 -> 1866000 | D11: Management Fee | E11: =Assumptions!$B$20 -> 0.04
A12: Levered IRR | B12: ='Cash Flow & Returns'!$B$31 -> 0.17490657 | D12: Year 1 DSCR | E12: ='Debt Schedule'!$B$20 -> 1.4614008
A13: Equity Multiple | B13: ='Cash Flow & Returns'!$B$33 -> 2.0510669
A14: Avg. Cash-on-Cash (Yrs 1-5) | B14: ='Cash Flow & Returns'!$B$34 -> 0.099538851
A16: ✓ Underwriting Approach: Conservative Exit Cap Rate
A17: Going-In Cap Rate (Purchase) | C17: =$B$8 -> 0.078337235
A18: Assumed Exit Cap Rate (Sale) | C18: =$B$10 -> 0.08
A19: Underwriting Cushion (Exit minus Going-In) | C19: =C18-C17 -> 0.0016627653
A21: • The model buys at a 7.83% cap rate and underwrites the Year-5 sale at a slightly higher 8.00% cap rate — a ~17 bps cushion, not a bet on compression.
A22: • Assuming the exit cap rate is flat or higher than the going-in cap is standard practice, especially on a 5+ year hold where cap rate cycles are unpredictable.
A23: • The upside of this: the returns already work even if the market softens a bit by the time we sell.
A24: • If cap rates hold steady or improve instead, that's extra return on top — not something we're counting on to hit our numbers.
A25: • The scenario table below shows the deal still performs even under a tougher exit than we assumed.
A27: Scenario Comparison: Exit Cap Rate Range
A28: Scenario | C28: Exit Cap Rate | D28: Levered IRR | E28: Equity Multiple
A29: Base Case (Conservative, +17 bps cushion) | C29: =$B$10 -> 0.08 | D29: ='Cash Flow & Returns'!$B$31 -> 0.17490657 | E29: ='Cash Flow & Returns'!$B$33 -> 2.0510669
A30: Upside (Flat, exit = going-in cap, no cushion) | C30: =$B$8 -> 0.078337235 | D30: =IRR(K50:P50) -> 0.1843177 | E30: =SUM(L50:P50)/'Cash Flow & Returns'!$B$7 -> 2.1303004
A31: Downside (Cap rate expands another 50 bps) | C31: =$B$10+0.005 -> 0.085 | D31: =IRR(K51:P51) -> 0.14698357 | E31: =SUM(L51:P51)/'Cash Flow & Returns'!$B$7 -> 1.8314847
A32: Bottom Line
A33: Pass — conservative underwriting, returns hold up across a realistic cap rate range
A34: • Base case assumes a modest 17 bps of cap rate expansion by exit (8.00% vs. 7.83% going-in) — the return does not rely on the market getting more generous.
A35: • Levered IRR of 17.5% clears the 15% target even under this conservative assumption, with 2.05x equity multiple over the 5-year hold.
A36: • Even a further 50 bps of cap rate expansion (a real downside case) only brings the IRR to ~14.7% — close to target, not a cliff — while any compression back toward today's pricing is pure upside.
J49: Helper (CF0-CF5) — do not edit:
K50: ='Cash Flow & Returns'!$B$27 -> -1866000 | L50: ='Cash Flow & Returns'!$C$27 -> 153839.42 | M50: ='Cash Flow & Returns'!$D$27 -> 169297.14 | N50: ='Cash Flow & Returns'!$E$27 -> 185239.6 | O50: ='Cash Flow & Returns'!$F$27 -> 201681.86 | P50: ='Operating Expenses'!$F$21-'Debt Schedule'!$F$18+(Sensitivity!$O$12/$C$30*(1-Assumptions!$B$34)-'Debt Schedule'!$F$17) -> 3265082.5
K51: ='Cash Flow & Returns'!$B$27 -> -1866000 | L51: ='Cash Flow & Returns'!$C$27 -> 153839.42 | M51: ='Cash Flow & Returns'!$D$27 -> 169297.14 | N51: ='Cash Flow & Returns'!$E$27 -> 185239.6 | O51: ='Cash Flow & Returns'!$F$27 -> 201681.86 | P51: ='Operating Expenses'!$F$21-'Debt Schedule'!$F$18+(Sensitivity!$O$12/$C$31*(1-Assumptions!$B$34)-'Debt Schedule'!$F$17) -> 2707492.3

Sheet Assumptions
A1: Multi-Family Acquisition Model — Assumptions
A2: All green cells are placeholder inputs — replace with your property's actual data.
A4: Property Overview | D4: Units | E4: Row 8
A5: Property Name | B5: Sample Gardens Apartments | D5: Purchase Price | E5: Row 10
A6: Address | B6: 123 Main St, Anytown, USA | D6: Total Acquisition Cost | E6: Row 13
A7: Number of Units | B7: 40 | D7: Vacancy % | E7: Row 16
A8: Year Built | B8: 1998 | D8: Rent Growth % | E8: Row 17
A9: Rentable Square Feet | B9: 34000 | D9: Expense Growth % | E9: Row 18
A10: Purchase Price | B10: 6000000 | D10: Other Income/unit/mo | E10: Row 19
A11: Closing Costs (% of Price) | B11: 0.02 | D11: Management Fee % | E11: Row 20
A12: CapEx Reserve at Close ($/unit) | B12: 2500 | D12: Reserves/unit/yr | E12: Row 21
A13: Total Acquisition Cost | B13: =B10*(1+B11)+B12*B7 -> 6220000 | D13: Loan Amount | E13: Row 25
D14: Interest Rate | E14: Row 26
A15: Operating Assumptions | D15: Amortization Yrs | E15: Row 27
A16: Vacancy & Credit Loss | B16: 0.05 | D16: Loan Term Yrs | E16: Row 28
A17: Annual Rent Growth | B17: 0.03 | D17: IO Period Yrs | E17: Row 29
A18: Annual Expense Growth | B18: 0.025 | D18: Hold Period Yrs | E18: Row 32
A19: Other Income ($/unit/month) | B19: 35 | D19: Exit Cap Rate | E19: Row 33
A20: Management Fee (% of EGI) | B20: 0.04 | D20: Selling Costs % | E20: Row 34
A21: Replacement Reserves ($/unit/yr) | B21: 300
A23: Financing Assumptions
A24: Loan-to-Value (LTV) | B24: 0.7
A25: Loan Amount | B25: =B13*B24 -> 4354000
A26: Interest Rate (Annual) | B26: 0.065
A27: Amortization Period (Years) | B27: 30
A28: Loan Term (Years) | B28: 10
A29: Interest-Only Period (Years) | B29: 0
A31: Exit & Return Assumptions
A32: Hold Period (Years) | B32: 5
A33: Exit Capitalization Rate | B33: 0.08
A34: Selling Costs (% of Sale Price) | B34: 0.02
A35: Target Levered IRR | B35: 0.15
A37: Reference Cells (linked by other tabs)

Sheet Rent Roll
A1: Multi-Family Acquisition Model — Rent Roll / Revenue
A2: Blue cells are placeholder inputs — replace with your property's actual unit mix.
A4: Unit Mix & Market Rents
A5: Unit Type | B5: # of Units | C5: Avg SF/Unit | D5: Market Rent ($/unit/mo) | E5: Monthly Rent ($) | F5: Annual Rent ($)
A6: Studio | B6: 8 | C6: 550 | D6: 1150 | E6: =B6*D6 -> 9200 | F6: =E6*12 -> 110400
A7: 1BR / 1BA | B7: 16 | C7: 725 | D7: 1350 | E7: =B7*D7 -> 21600 | F7: =E7*12 -> 259200
A8: 2BR / 2BA | B8: 12 | C8: 975 | D8: 1650 | E8: =B8*D8 -> 19800 | F8: =E8*12 -> 237600
A9: 3BR / 2BA | B9: 4 | C9: 1200 | D9: 1950 | E9: =B9*D9 -> 7800 | F9: =E9*12 -> 93600
A10: Total / Weighted Avg | B10: =SUM(B6:B9) -> 40 | C10: =SUMPRODUCT(B6:B9,C6:C9)/B10 -> 812.5 | D10: =SUMPRODUCT(B6:B9,D6:D9)/B10 -> 1460 | E10: =SUM(E6:E9) -> 58400 | F10: =SUM(F6:F9) -> 700800
A11: Check: Total Units vs. Assumptions | B11: =IF(B10=Assumptions!B7,"OK","Mismatch — update unit mix or Assumptions!B7") -> OK
A13: 5-Year Revenue Projection
B14: =1 -> 1 | C14: =B14+1 -> 2 | D14: =C14+1 -> 3 | E14: =D14+1 -> 4 | F14: =E14+1 -> 5
A15: Gross Potential Rent (GPR) | B15: =$F$10 -> 700800 | C15: =B15*(1+Assumptions!$B$17) -> 721824 | D15: =C15*(1+Assumptions!$B$17) -> 743478.72 | E15: =D15*(1+Assumptions!$B$17) -> 765783.08 | F15: =E15*(1+Assumptions!$B$17) -> 788756.57
A16: Vacancy & Credit Loss | B16: =-B15*Assumptions!$B$16 -> -35040 | C16: =-C15*Assumptions!$B$16 -> -36091.2 | D16: =-D15*Assumptions!$B$16 -> -37173.936 | E16: =-E15*Assumptions!$B$16 -> -38289.154 | F16: =-F15*Assumptions!$B$16 -> -39437.829
A17: Net Rental Income | B17: =B15+B16 -> 665760 | C17: =C15+C16 -> 685732.8 | D17: =D15+D16 -> 706304.78 | E17: =E15+E16 -> 727493.93 | F17: =F15+F16 -> 749318.75
A18: Other Income | B18: =(Assumptions!$B$19*Assumptions!$B$7)*12 -> 16800 | C18: =B18*(1+Assumptions!$B$17) -> 17304 | D18: =C18*(1+Assumptions!$B$17) -> 17823.12 | E18: =D18*(1+Assumptions!$B$17) -> 18357.814 | F18: =E18*(1+Assumptions!$B$17) -> 18908.548
A19: Effective Gross Income (EGI) | B19: =B17+B18 -> 682560 | C19: =C17+C18 -> 703036.8 | D19: =D17+D18 -> 724127.9 | E19: =E17+E18 -> 745851.74 | F19: =F17+F18 -> 768227.29

Sheet Operating Expenses
A1: Multi-Family Acquisition Model — Operating Expenses
A2: Blue cells are placeholder inputs — replace with your property's actual expense data.
A4: Year 1 Expense Assumptions
A5: Expense Category | B5: $/Unit/Year | C5: Year 1 Total ($)
A6: Property Taxes | B6: 1500 | C6: =B6*Assumptions!$B$7 -> 60000
A7: Insurance | B7: 500 | C7: =B7*Assumptions!$B$7 -> 20000
A8: Repairs & Maintenance | B8: 800 | C8: =B8*Assumptions!$B$7 -> 32000
A9: Utilities | B9: 600 | C9: =B9*Assumptions!$B$7 -> 24000
A10: General & Administrative | B10: 300 | C10: =B10*Assumptions!$B$7 -> 12000
A11: Marketing & Leasing | B11: 200 | C11: =B11*Assumptions!$B$7 -> 8000
A12: Subtotal — Fixed/Controllable Opex | B12: =SUM(B6:B11) -> 3900 | C12: =SUM(C6:C11) -> 156000
A14: 5-Year Operating Expense & NOI Projection
B15: =1 -> 1 | C15: =B15+1 -> 2 | D15: =C15+1 -> 3 | E15: =D15+1 -> 4 | F15: =E15+1 -> 5
A16: Fixed/Controllable Opex | B16: =$C$12 -> 156000 | C16: =B16*(1+Assumptions!$B$18) -> 159900 | D16: =C16*(1+Assumptions!$B$18) -> 163897.5 | E16: =D16*(1+Assumptions!$B$18) -> 167994.94 | F16: =E16*(1+Assumptions!$B$18) -> 172194.81
A17: Management Fee | B17: =Assumptions!$B$20*'Rent Roll'!B19 -> 27302.4 | C17: =Assumptions!$B$20*'Rent Roll'!C19 -> 28121.472 | D17: =Assumptions!$B$20*'Rent Roll'!D19 -> 28965.116 | E17: =Assumptions!$B$20*'Rent Roll'!E19 -> 29834.07 | F17: =Assumptions!$B$20*'Rent Roll'!F19 -> 30729.092
A18: Replacement Reserves | B18: =Assumptions!$B$21*Assumptions!$B$7 -> 12000 | C18: =B18*(1+Assumptions!$B$18) -> 12300 | D18: =C18*(1+Assumptions!$B$18) -> 12607.5 | E18: =D18*(1+Assumptions!$B$18) -> 12922.687 | F18: =E18*(1+Assumptions!$B$18) -> 13245.755
A19: Total Operating Expenses | B19: =SUM(B16:B18) -> 195302.4 | C19: =SUM(C16:C18) -> 200321.47 | D19: =SUM(D16:D18) -> 205470.12 | E19: =SUM(E16:E18) -> 210751.69 | F19: =SUM(F16:F18) -> 216169.66
A20: Effective Gross Income (EGI) | B20: ='Rent Roll'!B19 -> 682560 | C20: ='Rent Roll'!C19 -> 703036.8 | D20: ='Rent Roll'!D19 -> 724127.9 | E20: ='Rent Roll'!E19 -> 745851.74 | F20: ='Rent Roll'!F19 -> 768227.29
A21: Net Operating Income (NOI) | B21: =B20-B19 -> 487257.6 | C21: =C20-C19 -> 502715.33 | D21: =D20-D19 -> 518657.79 | E21: =E20-E19 -> 535100.05 | F21: =F20-F19 -> 552057.64

Sheet Debt Schedule
A1: Multi-Family Acquisition Model — Debt Schedule
A2: Green cells link from Assumptions; all loan terms are set there.
A4: Loan Terms
A5: Loan Amount | B5: =Assumptions!$B$25 -> 4354000
A6: Interest Rate (Annual) | B6: =Assumptions!$B$26 -> 0.065
A7: Amortization Period (Years) | B7: =Assumptions!$B$27 -> 30
A8: Loan Term (Years) | B8: =Assumptions!$B$28 -> 10
A9: Interest-Only Period (Years) | B9: =Assumptions!$B$29 -> 0
A10: Annual Debt Service (Amortizing) | B10: =-PMT(B6,B7,B5) -> 333418.18
A12: 5-Year Amortization & DSCR
B13: =1 -> 1 | C13: =B13+1 -> 2 | D13: =C13+1 -> 3 | E13: =D13+1 -> 4 | F13: =E13+1 -> 5
A14: Beginning Balance | B14: =$B$5 -> 4354000 | C14: =B17 -> 4303591.8 | D14: =C17 -> 4249907.1 | E14: =D17 -> 4192732.9 | F14: =E17 -> 4131842.3
A15: Interest Payment | B15: =B14*$B$6 -> 283010 | C15: =C14*$B$6 -> 279733.47 | D15: =D14*$B$6 -> 276243.96 | E15: =E14*$B$6 -> 272527.64 | F15: =F14*$B$6 -> 268569.75
A16: Principal Payment | B16: =IF(B13<=$B$9,0,$B$10-B15) -> 50408.184 | C16: =IF(C13<=$B$9,0,$B$10-C15) -> 53684.715 | D16: =IF(D13<=$B$9,0,$B$10-D15) -> 57174.222 | E16: =IF(E13<=$B$9,0,$B$10-E15) -> 60890.546 | F16: =IF(F13<=$B$9,0,$B$10-F15) -> 64848.432
A17: Ending Balance | B17: =B14-B16 -> 4303591.8 | C17: =C14-C16 -> 4249907.1 | D17: =D14-D16 -> 4192732.9 | E17: =E14-E16 -> 4131842.3 | F17: =F14-F16 -> 4066993.9
A18: Total Debt Service | B18: =B15+B16 -> 333418.18 | C18: =C15+C16 -> 333418.18 | D18: =D15+D16 -> 333418.18 | E18: =E15+E16 -> 333418.18 | F18: =F15+F16 -> 333418.18
A19: Net Operating Income (NOI) | B19: ='Operating Expenses'!B21 -> 487257.6 | C19: ='Operating Expenses'!C21 -> 502715.33 | D19: ='Operating Expenses'!D21 -> 518657.79 | E19: ='Operating Expenses'!E21 -> 535100.05 | F19: ='Operating Expenses'!F21 -> 552057.64
A20: DSCR (NOI / Debt Service) | B20: =B19/B18 -> 1.4614008 | C20: =C19/C18 -> 1.5077622 | D20: =D19/D18 -> 1.5555774 | E20: =E19/E18 -> 1.6048916 | F20: =F19/F18 -> 1.6557514

Sheet Cash Flow & Returns
A1: Multi-Family Acquisition Model — Cash Flow & Returns
A2: Green cells link from other tabs; all inputs are set in Assumptions.
A4: Investment Summary
A5: Total Acquisition Cost | B5: =Assumptions!$B$13 -> 6220000
A6: Loan Amount | B6: =Assumptions!$B$25 -> 4354000
A7: Initial Equity Investment | B7: =B5-B6 -> 1866000
A9: Exit Valuation (End of Hold Period)
A10: Hold Period (Years) | B10: =Assumptions!$B$32 -> 5
A11: Forward NOI (Year 6 Estimate) | B11: ='Debt Schedule'!F19*(1+Assumptions!$B$17) -> 568619.37
A12: Exit Capitalization Rate | B12: =Assumptions!$B$33 -> 0.08
A13: Gross Sale Price | B13: =B11/B12 -> 7107742.1
A14: Selling Costs | B14: =-B13*Assumptions!$B$34 -> -142154.84
A15: Net Sale Proceeds (before loan payoff) | B15: =B13+B14 -> 6965587.2
A16: Loan Payoff (Ending Balance) | B16: =-'Debt Schedule'!F17 -> -4066993.9
A17: Net Sale Proceeds to Equity | B17: =B15+B16 -> 2898593.3
A19: Unlevered & Levered Cash Flow
B20: =0 -> 0 | C20: =B20+1 -> 1 | D20: =C20+1 -> 2 | E20: =D20+1 -> 3 | F20: =E20+1 -> 4 | G20: =F20+1 -> 5
A21: NOI | C21: ='Operating Expenses'!B21 -> 487257.6 | D21: ='Operating Expenses'!C21 -> 502715.33 | E21: ='Operating Expenses'!D21 -> 518657.79 | F21: ='Operating Expenses'!E21 -> 535100.05 | G21: ='Operating Expenses'!F21 -> 552057.64
A22: Net Sale Proceeds (Unlevered) | G22: =B15 -> 6965587.2
A23: Unlevered Cash Flow | B23: =-B5 -> -6220000 | C23: =C21+C22 -> 487257.6 | D23: =D21+D22 -> 502715.33 | E23: =E21+E22 -> 518657.79 | F23: =F21+F22 -> 535100.05 | G23: =G21+G22 -> 7517644.9
A25: Debt Service | C25: =-'Debt Schedule'!B18 -> -333418.18 | D25: =-'Debt Schedule'!C18 -> -333418.18 | E25: =-'Debt Schedule'!D18 -> -333418.18 | F25: =-'Debt Schedule'!E18 -> -333418.18 | G25: =-'Debt Schedule'!F18 -> -333418.18
A26: Net Sale Proceeds (Levered) | G26: =B17 -> 2898593.3
A27: Levered Cash Flow | B27: =-B7 -> -1866000 | C27: =C21+C25 -> 153839.42 | D27: =D21+D25 -> 169297.14 | E27: =E21+E25 -> 185239.6 | F27: =F21+F25 -> 201681.86 | G27: =G21+G25+G26 -> 3117232.8
A29: Return Metrics
A30: Unlevered IRR | B30: =IRR(B23:G23) -> 0.10249718
A31: Levered IRR | B31: =IRR(B27:G27) -> 0.17490657
A32: Target Levered IRR | B32: =Assumptions!$B$35 -> 0.15
A33: Equity Multiple (Levered) | B33: =SUM(C27:G27)/B7 -> 2.0510669
A34: Average Cash-on-Cash Return (Yrs 1-5, excl. sale) | B34: =AVERAGE(C27:F27,G21+G25)/B7 -> 0.099538851
A35: Year 1 Cash-on-Cash Return | B35: =C27/B7 -> 0.082443417

Sheet Sensitivity
A1: Multi-Family Acquisition Model — Sensitivity Dashboard
A2: Levered IRR sensitized to Exit Cap Rate and Annual Rent Growth. Base case (center) is highlighted.
A4: Levered IRR: Exit Cap Rate vs. Rent Growth | I4: Step Sizes (inputs)
I5: Exit Cap Rate Step | J5: 0.005
B6: Rent Growth \ Exit Cap Rate | C6: =Assumptions!$B$33-2*$J$5 -> 0.07 | D6: =Assumptions!$B$33-1*$J$5 -> 0.075 | E6: =Assumptions!$B$33 -> 0.08 | F6: =Assumptions!$B$33+1*$J$5 -> 0.085 | G6: =Assumptions!$B$33+2*$J$5 -> 0.09 | I6: Rent Growth Step | J6: 0.005
B7: =Assumptions!$B$17-2*$J$6 -> 0.02 | C7: =$P18 -> 0.20149049 | D7: =$P19 -> 0.17064574 | E7: =$P20 -> 0.14047344 | F7: =$P21 -> 0.11066503 | G7: =$P22 -> 0.08091414
B8: =Assumptions!$B$17-1*$J$6 -> 0.025 | C8: =$P23 -> 0.2174342 | D8: =$P24 -> 0.18733849 | E8: =$P25 -> 0.15803216 | F8: =$P26 -> 0.1292317 | G8: =$P27 -> 0.10066513 | I8: Helper: NOI by Rent Growth Scenario (feeds grid below — do not edit)
B9: =Assumptions!$B$17 -> 0.03 | C9: =$P28 -> 0.23288328 | D9: =$P29 -> 0.20345152 | E9: =$P30 -> 0.17490657 | F9: =$P31 -> 0.14698357 | G9: =$P32 -> 0.11943556 | I9: Growth Rate | J9: NOI Yr1 | K9: NOI Yr2 | L9: NOI Yr3 | M9: NOI Yr4 | N9: NOI Yr5 | O9: NOI Yr6 (Fwd)
B10: =Assumptions!$B$17+1*$J$6 -> 0.035 | C10: =$P33 -> 0.247884 | D10: =$P34 -> 0.21904353 | E10: =$P35 -> 0.19117195 | F10: =$P36 -> 0.16401839 | G10: =$P37 -> 0.13735445 | I10: =B7 -> 0.02 | J10: ='Rent Roll'!$B$19*(1-Assumptions!$B$20)*(1+$I10)^0-('Operating Expenses'!$B$16+'Operating Expenses'!$B$18) -> 487257.6 | K10: ='Rent Roll'!$B$19*(1-Assumptions!$B$20)*(1+$I10)^1-('Operating Expenses'!$C$16+'Operating Expenses'!$C$18) -> 496162.75 | L10: ='Rent Roll'!$B$19*(1-Assumptions!$B$20)*(1+$I10)^2-('Operating Expenses'!$D$16+'Operating Expenses'!$D$18) -> 505225.01 | M10: ='Rent Roll'!$B$19*(1-Assumptions!$B$20)*(1+$I10)^3-('Operating Expenses'!$E$16+'Operating Expenses'!$E$18) -> 514446.98 | N10: ='Rent Roll'!$B$19*(1-Assumptions!$B$20)*(1+$I10)^4-('Operating Expenses'!$F$16+'Operating Expenses'!$F$18) -> 523831.33 | O10: =N10*(1+$I10) -> 534307.96
B11: =Assumptions!$B$17+2*$J$6 -> 0.04 | C11: =$P38 -> 0.2624764 | D11: =$P39 -> 0.23416464 | E11: =$P40 -> 0.20689162 | F11: =$P41 -> 0.18041707 | G11: =$P42 -> 0.15452645 | I11: =B8 -> 0.025 | J11: ='Rent Roll'!$B$19*(1-Assumptions!$B$20)*(1+$I11)^0-('Operating Expenses'!$B$16+'Operating Expenses'!$B$18) -> 487257.6 | K11: ='Rent Roll'!$B$19*(1-Assumptions!$B$20)*(1+$I11)^1-('Operating Expenses'!$C$16+'Operating Expenses'!$C$18) -> 499439.04 | L11: ='Rent Roll'!$B$19*(1-Assumptions!$B$20)*(1+$I11)^2-('Operating Expenses'!$D$16+'Operating Expenses'!$D$18) -> 511925.02 | M11: ='Rent Roll'!$B$19*(1-Assumptions!$B$20)*(1+$I11)^3-('Operating Expenses'!$E$16+'Operating Expenses'!$E$18) -> 524723.14 | N11: ='Rent Roll'!$B$19*(1-Assumptions!$B$20)*(1+$I11)^4-('Operating Expenses'!$F$16+'Operating Expenses'!$F$18) -> 537841.22 | O11: =N11*(1+$I11) -> 551287.25
I12: =B9 -> 0.03 | J12: ='Rent Roll'!$B$19*(1-Assumptions!$B$20)*(1+$I12)^0-('Operating Expenses'!$B$16+'Operating Expenses'!$B$18) -> 487257.6 | K12: ='Rent Roll'!$B$19*(1-Assumptions!$B$20)*(1+$I12)^1-('Operating Expenses'!$C$16+'Operating Expenses'!$C$18) -> 502715.33 | L12: ='Rent Roll'!$B$19*(1-Assumptions!$B$20)*(1+$I12)^2-('Operating Expenses'!$D$16+'Operating Expenses'!$D$18) -> 518657.79 | M12: ='Rent Roll'!$B$19*(1-Assumptions!$B$20)*(1+$I12)^3-('Operating Expenses'!$E$16+'Operating Expenses'!$E$18) -> 535100.05 | N12: ='Rent Roll'!$B$19*(1-Assumptions!$B$20)*(1+$I12)^4-('Operating Expenses'!$F$16+'Operating Expenses'!$F$18) -> 552057.64 | O12: =N12*(1+$I12) -> 568619.37
I13: =B10 -> 0.035 | J13: ='Rent Roll'!$B$19*(1-Assumptions!$B$20)*(1+$I13)^0-('Operating Expenses'!$B$16+'Operating Expenses'!$B$18) -> 487257.6 | K13: ='Rent Roll'!$B$19*(1-Assumptions!$B$20)*(1+$I13)^1-('Operating Expenses'!$C$16+'Operating Expenses'!$C$18) -> 505991.62 | L13: ='Rent Roll'!$B$19*(1-Assumptions!$B$20)*(1+$I13)^2-('Operating Expenses'!$D$16+'Operating Expenses'!$D$18) -> 525423.32 | M13: ='Rent Roll'!$B$19*(1-Assumptions!$B$20)*(1+$I13)^3-('Operating Expenses'!$E$16+'Operating Expenses'!$E$18) -> 545578.19 | N13: ='Rent Roll'!$B$19*(1-Assumptions!$B$20)*(1+$I13)^4-('Operating Expenses'!$F$16+'Operating Expenses'!$F$18) -> 566482.6 | O13: =N13*(1+$I13) -> 586309.49
I14: =B11 -> 0.04 | J14: ='Rent Roll'!$B$19*(1-Assumptions!$B$20)*(1+$I14)^0-('Operating Expenses'!$B$16+'Operating Expenses'!$B$18) -> 487257.6 | K14: ='Rent Roll'!$B$19*(1-Assumptions!$B$20)*(1+$I14)^1-('Operating Expenses'!$C$16+'Operating Expenses'!$C$18) -> 509267.9 | L14: ='Rent Roll'!$B$19*(1-Assumptions!$B$20)*(1+$I14)^2-('Operating Expenses'!$D$16+'Operating Expenses'!$D$18) -> 532221.62 | M14: ='Rent Roll'!$B$19*(1-Assumptions!$B$20)*(1+$I14)^3-('Operating Expenses'!$E$16+'Operating Expenses'!$E$18) -> 556158.06 | N14: ='Rent Roll'!$B$19*(1-Assumptions!$B$20)*(1+$I14)^4-('Operating Expenses'!$F$16+'Operating Expenses'!$F$18) -> 581118.15 | O14: =N14*(1+$I14) -> 604362.87
I16: Helper: Levered Cash Flow & IRR per Scenario (do not edit)
I17: Scenario | J17: CF0 | K17: CF1 | L17: CF2 | M17: CF3 | N17: CF4 | O17: CF5 | P17: IRR
I18: Growth Row 1 x Cap Col 1 | J18: =-'Cash Flow & Returns'!$B$7 -> -1866000 | K18: =$J10-'Debt Schedule'!$B$18 -> 153839.42 | L18: =$K10-'Debt Schedule'!$C$18 -> 162744.57 | M18: =$L10-'Debt Schedule'!$D$18 -> 171806.82 | N18: =$M10-'Debt Schedule'!$E$18 -> 181028.8 | O18: =$N10-'Debt Schedule'!$F$18+$O10/C$6*(1-Assumptions!$B$34)-'Debt Schedule'!$F$17 -> 3603730.7 | P18: =IRR(J18:O18) -> 0.20149049
I19: Growth Row 1 x Cap Col 2 | J19: =-'Cash Flow & Returns'!$B$7 -> -1866000 | K19: =$J10-'Debt Schedule'!$B$18 -> 153839.42 | L19: =$K10-'Debt Schedule'!$C$18 -> 162744.57 | M19: =$L10-'Debt Schedule'!$D$18 -> 171806.82 | N19: =$M10-'Debt Schedule'!$E$18 -> 181028.8 | O19: =$N10-'Debt Schedule'!$F$18+$O10/D$6*(1-Assumptions!$B$34)-'Debt Schedule'!$F$17 -> 3105043.3 | P19: =IRR(J19:O19) -> 0.17064574
I20: Growth Row 1 x Cap Col 3 | J20: =-'Cash Flow & Returns'!$B$7 -> -1866000 | K20: =$J10-'Debt Schedule'!$B$18 -> 153839.42 | L20: =$K10-'Debt Schedule'!$C$18 -> 162744.57 | M20: =$L10-'Debt Schedule'!$D$18 -> 171806.82 | N20: =$M10-'Debt Schedule'!$E$18 -> 181028.8 | O20: =$N10-'Debt Schedule'!$F$18+$O10/E$6*(1-Assumptions!$B$34)-'Debt Schedule'!$F$17 -> 2668691.8 | P20: =IRR(J20:O20) -> 0.14047344
I21: Growth Row 1 x Cap Col 4 | J21: =-'Cash Flow & Returns'!$B$7 -> -1866000 | K21: =$J10-'Debt Schedule'!$B$18 -> 153839.42 | L21: =$K10-'Debt Schedule'!$C$18 -> 162744.57 | M21: =$L10-'Debt Schedule'!$D$18 -> 171806.82 | N21: =$M10-'Debt Schedule'!$E$18 -> 181028.8 | O21: =$N10-'Debt Schedule'!$F$18+$O10/F$6*(1-Assumptions!$B$34)-'Debt Schedule'!$F$17 -> 2283675.7 | P21: =IRR(J21:O21) -> 0.11066503
I22: Growth Row 1 x Cap Col 5 | J22: =-'Cash Flow & Returns'!$B$7 -> -1866000 | K22: =$J10-'Debt Schedule'!$B$18 -> 153839.42 | L22: =$K10-'Debt Schedule'!$C$18 -> 162744.57 | M22: =$L10-'Debt Schedule'!$D$18 -> 171806.82 | N22: =$M10-'Debt Schedule'!$E$18 -> 181028.8 | O22: =$N10-'Debt Schedule'!$F$18+$O10/G$6*(1-Assumptions!$B$34)-'Debt Schedule'!$F$17 -> 1941439.3 | P22: =IRR(J22:O22) -> 0.08091414
I23: Growth Row 2 x Cap Col 1 | J23: =-'Cash Flow & Returns'!$B$7 -> -1866000 | K23: =$J11-'Debt Schedule'!$B$18 -> 153839.42 | L23: =$K11-'Debt Schedule'!$C$18 -> 166020.86 | M23: =$L11-'Debt Schedule'!$D$18 -> 178506.83 | N23: =$M11-'Debt Schedule'!$E$18 -> 191304.96 | O23: =$N11-'Debt Schedule'!$F$18+$O11/C$6*(1-Assumptions!$B$34)-'Debt Schedule'!$F$17 -> 3855450.6 | P23: =IRR(J23:O23) -> 0.2174342
I24: Growth Row 2 x Cap Col 2 | J24: =-'Cash Flow & Returns'!$B$7 -> -1866000 | K24: =$J11-'Debt Schedule'!$B$18 -> 153839.42 | L24: =$K11-'Debt Schedule'!$C$18 -> 166020.86 | M24: =$L11-'Debt Schedule'!$D$18 -> 178506.83 | N24: =$M11-'Debt Schedule'!$E$18 -> 191304.96 | O24: =$N11-'Debt Schedule'!$F$18+$O11/D$6*(1-Assumptions!$B$34)-'Debt Schedule'!$F$17 -> 3340915.9 | P24: =IRR(J24:O24) -> 0.18733849
I25: Growth Row 2 x Cap Col 3 | J25: =-'Cash Flow & Returns'!$B$7 -> -1866000 | K25: =$J11-'Debt Schedule'!$B$18 -> 153839.42 | L25: =$K11-'Debt Schedule'!$C$18 -> 166020.86 | M25: =$L11-'Debt Schedule'!$D$18 -> 178506.83 | N25: =$M11-'Debt Schedule'!$E$18 -> 191304.96 | O25: =$N11-'Debt Schedule'!$F$18+$O11/E$6*(1-Assumptions!$B$34)-'Debt Schedule'!$F$17 -> 2890698 | P25: =IRR(J25:O25) -> 0.15803216
I26: Growth Row 2 x Cap Col 4 | J26: =-'Cash Flow & Returns'!$B$7 -> -1866000 | K26: =$J11-'Debt Schedule'!$B$18 -> 153839.42 | L26: =$K11-'Debt Schedule'!$C$18 -> 166020.86 | M26: =$L11-'Debt Schedule'!$D$18 -> 178506.83 | N26: =$M11-'Debt Schedule'!$E$18 -> 191304.96 | O26: =$N11-'Debt Schedule'!$F$18+$O11/F$6*(1-Assumptions!$B$34)-'Debt Schedule'!$F$17 -> 2493446.8 | P26: =IRR(J26:O26) -> 0.1292317
I27: Growth Row 2 x Cap Col 5 | J27: =-'Cash Flow & Returns'!$B$7 -> -1866000 | K27: =$J11-'Debt Schedule'!$B$18 -> 153839.42 | L27: =$K11-'Debt Schedule'!$C$18 -> 166020.86 | M27: =$L11-'Debt Schedule'!$D$18 -> 178506.83 | N27: =$M11-'Debt Schedule'!$E$18 -> 191304.96 | O27: =$N11-'Debt Schedule'!$F$18+$O11/G$6*(1-Assumptions!$B$34)-'Debt Schedule'!$F$17 -> 2140334.8 | P27: =IRR(J27:O27) -> 0.10066513
I28: Growth Row 3 x Cap Col 1 | J28: =-'Cash Flow & Returns'!$B$7 -> -1866000 | K28: =$J12-'Debt Schedule'!$B$18 -> 153839.42 | L28: =$K12-'Debt Schedule'!$C$18 -> 169297.14 | M28: =$L12-'Debt Schedule'!$D$18 -> 185239.6 | N28: =$M12-'Debt Schedule'!$E$18 -> 201681.86 | O28: =$N12-'Debt Schedule'!$F$18+$O12/C$6*(1-Assumptions!$B$34)-'Debt Schedule'!$F$17 -> 4112316.7 | P28: =IRR(J28:O28) -> 0.23288328
I29: Growth Row 3 x Cap Col 2 | J29: =-'Cash Flow & Returns'!$B$7 -> -1866000 | K29: =$J12-'Debt Schedule'!$B$18 -> 153839.42 | L29: =$K12-'Debt Schedule'!$C$18 -> 169297.14 | M29: =$L12-'Debt Schedule'!$D$18 -> 185239.6 | N29: =$M12-'Debt Schedule'!$E$18 -> 201681.86 | O29: =$N12-'Debt Schedule'!$F$18+$O12/D$6*(1-Assumptions!$B$34)-'Debt Schedule'!$F$17 -> 3581605.3 | P29: =IRR(J29:O29) -> 0.20345152
I30: Growth Row 3 x Cap Col 3 (BASE CASE) | J30: =-'Cash Flow & Returns'!$B$7 -> -1866000 | K30: =$J12-'Debt Schedule'!$B$18 -> 153839.42 | L30: =$K12-'Debt Schedule'!$C$18 -> 169297.14 | M30: =$L12-'Debt Schedule'!$D$18 -> 185239.6 | N30: =$M12-'Debt Schedule'!$E$18 -> 201681.86 | O30: =$N12-'Debt Schedule'!$F$18+$O12/E$6*(1-Assumptions!$B$34)-'Debt Schedule'!$F$17 -> 3117232.8 | P30: =IRR(J30:O30) -> 0.17490657
I31: Growth Row 3 x Cap Col 4 | J31: =-'Cash Flow & Returns'!$B$7 -> -1866000 | K31: =$J12-'Debt Schedule'!$B$18 -> 153839.42 | L31: =$K12-'Debt Schedule'!$C$18 -> 169297.14 | M31: =$L12-'Debt Schedule'!$D$18 -> 185239.6 | N31: =$M12-'Debt Schedule'!$E$18 -> 201681.86 | O31: =$N12-'Debt Schedule'!$F$18+$O12/F$6*(1-Assumptions!$B$34)-'Debt Schedule'!$F$17 -> 2707492.3 | P31: =IRR(J31:O31) -> 0.14698357
I32: Growth Row 3 x Cap Col 5 | J32: =-'Cash Flow & Returns'!$B$7 -> -1866000 | K32: =$J12-'Debt Schedule'!$B$18 -> 153839.42 | L32: =$K12-'Debt Schedule'!$C$18 -> 169297.14 | M32: =$L12-'Debt Schedule'!$D$18 -> 185239.6 | N32: =$M12-'Debt Schedule'!$E$18 -> 201681.86 | O32: =$N12-'Debt Schedule'!$F$18+$O12/G$6*(1-Assumptions!$B$34)-'Debt Schedule'!$F$17 -> 2343278.6 | P32: =IRR(J32:O32) -> 0.11943556
I33: Growth Row 4 x Cap Col 1 | J33: =-'Cash Flow & Returns'!$B$7 -> -1866000 | K33: =$J13-'Debt Schedule'!$B$18 -> 153839.42 | L33: =$K13-'Debt Schedule'!$C$18 -> 172573.43 | M33: =$L13-'Debt Schedule'!$D$18 -> 192005.14 | N33: =$M13-'Debt Schedule'!$E$18 -> 212160.01 | O33: =$N13-'Debt Schedule'!$F$18+$O13/C$6*(1-Assumptions!$B$34)-'Debt Schedule'!$F$17 -> 4374403.4 | P33: =IRR(J33:O33) -> 0.247884
I34: Growth Row 4 x Cap Col 2 | J34: =-'Cash Flow & Returns'!$B$7 -> -1866000 | K34: =$J13-'Debt Schedule'!$B$18 -> 153839.42 | L34: =$K13-'Debt Schedule'!$C$18 -> 172573.43 | M34: =$L13-'Debt Schedule'!$D$18 -> 192005.14 | N34: =$M13-'Debt Schedule'!$E$18 -> 212160.01 | O34: =$N13-'Debt Schedule'!$F$18+$O13/D$6*(1-Assumptions!$B$34)-'Debt Schedule'!$F$17 -> 3827181.2 | P34: =IRR(J34:O34) -> 0.21904353
I35: Growth Row 4 x Cap Col 3 | J35: =-'Cash Flow & Returns'!$B$7 -> -1866000 | K35: =$J13-'Debt Schedule'!$B$18 -> 153839.42 | L35: =$K13-'Debt Schedule'!$C$18 -> 172573.43 | M35: =$L13-'Debt Schedule'!$D$18 -> 192005.14 | N35: =$M13-'Debt Schedule'!$E$18 -> 212160.01 | O35: =$N13-'Debt Schedule'!$F$18+$O13/E$6*(1-Assumptions!$B$34)-'Debt Schedule'!$F$17 -> 3348361.8 | P35: =IRR(J35:O35) -> 0.19117195
I36: Growth Row 4 x Cap Col 4 | J36: =-'Cash Flow & Returns'!$B$7 -> -1866000 | K36: =$J13-'Debt Schedule'!$B$18 -> 153839.42 | L36: =$K13-'Debt Schedule'!$C$18 -> 172573.43 | M36: =$L13-'Debt Schedule'!$D$18 -> 192005.14 | N36: =$M13-'Debt Schedule'!$E$18 -> 212160.01 | O36: =$N13-'Debt Schedule'!$F$18+$O13/F$6*(1-Assumptions!$B$34)-'Debt Schedule'!$F$17 -> 2925874.1 | P36: =IRR(J36:O36) -> 0.16401839
I37: Growth Row 4 x Cap Col 5 | J37: =-'Cash Flow & Returns'!$B$7 -> -1866000 | K37: =$J13-'Debt Schedule'!$B$18 -> 153839.42 | L37: =$K13-'Debt Schedule'!$C$18 -> 172573.43 | M37: =$L13-'Debt Schedule'!$D$18 -> 192005.14 | N37: =$M13-'Debt Schedule'!$E$18 -> 212160.01 | O37: =$N13-'Debt Schedule'!$F$18+$O13/G$6*(1-Assumptions!$B$34)-'Debt Schedule'!$F$17 -> 2550329.4 | P37: =IRR(J37:O37) -> 0.13735445
I38: Growth Row 5 x Cap Col 1 | J38: =-'Cash Flow & Returns'!$B$7 -> -1866000 | K38: =$J14-'Debt Schedule'!$B$18 -> 153839.42 | L38: =$K14-'Debt Schedule'!$C$18 -> 175849.72 | M38: =$L14-'Debt Schedule'!$D$18 -> 198803.44 | N38: =$M14-'Debt Schedule'!$E$18 -> 222739.88 | O38: =$N14-'Debt Schedule'!$F$18+$O14/C$6*(1-Assumptions!$B$34)-'Debt Schedule'!$F$17 -> 4641786.3 | P38: =IRR(J38:O38) -> 0.2624764
I39: Growth Row 5 x Cap Col 2 | J39: =-'Cash Flow & Returns'!$B$7 -> -1866000 | K39: =$J14-'Debt Schedule'!$B$18 -> 153839.42 | L39: =$K14-'Debt Schedule'!$C$18 -> 175849.72 | M39: =$L14-'Debt Schedule'!$D$18 -> 198803.44 | N39: =$M14-'Debt Schedule'!$E$18 -> 222739.88 | O39: =$N14-'Debt Schedule'!$F$18+$O14/D$6*(1-Assumptions!$B$34)-'Debt Schedule'!$F$17 -> 4077714.3 | P39: =IRR(J39:O39) -> 0.23416464
I40: Growth Row 5 x Cap Col 3 | J40: =-'Cash Flow & Returns'!$B$7 -> -1866000 | K40: =$J14-'Debt Schedule'!$B$18 -> 153839.42 | L40: =$K14-'Debt Schedule'!$C$18 -> 175849.72 | M40: =$L14-'Debt Schedule'!$D$18 -> 198803.44 | N40: =$M14-'Debt Schedule'!$E$18 -> 222739.88 | O40: =$N14-'Debt Schedule'!$F$18+$O14/E$6*(1-Assumptions!$B$34)-'Debt Schedule'!$F$17 -> 3584151.3 | P40: =IRR(J40:O40) -> 0.20689162
I41: Growth Row 5 x Cap Col 4 | J41: =-'Cash Flow & Returns'!$B$7 -> -1866000 | K41: =$J14-'Debt Schedule'!$B$18 -> 153839.42 | L41: =$K14-'Debt Schedule'!$C$18 -> 175849.72 | M41: =$L14-'Debt Schedule'!$D$18 -> 198803.44 | N41: =$M14-'Debt Schedule'!$E$18 -> 222739.88 | O41: =$N14-'Debt Schedule'!$F$18+$O14/F$6*(1-Assumptions!$B$34)-'Debt Schedule'!$F$17 -> 3148654.5 | P41: =IRR(J41:O41) -> 0.18041707
I42: Growth Row 5 x Cap Col 5 | J42: =-'Cash Flow & Returns'!$B$7 -> -1866000 | K42: =$J14-'Debt Schedule'!$B$18 -> 153839.42 | L42: =$K14-'Debt Schedule'!$C$18 -> 175849.72 | M42: =$L14-'Debt Schedule'!$D$18 -> 198803.44 | N42: =$M14-'Debt Schedule'!$E$18 -> 222739.88 | O42: =$N14-'Debt Schedule'!$F$18+$O14/G$6*(1-Assumptions!$B$34)-'Debt Schedule'!$F$17 -> 2761546.2 | P42: =IRR(J42:O42) -> 0.15452645
