Workbook

Sheet Assumptions
D1: Historical Results | I1: Forecast Period
D2: 2021 | E2: =+D2+1 -> 2022 | F2: =+E2+1 -> 2023 | G2: =+F2+1 -> 2024 | H2: =+G2+1 -> 2025 | I2: =+H2+1 -> 2026 | J2: =+I2+1 -> 2027 | K2: =+J2+1 -> 2028 | L2: =+K2+1 -> 2029 | M2: =+L2+1 -> 2030
A3: Balance Sheet Check | D3: =IF(ISNUMBER('Balance Sheet'!D23),IF(ABS('Balance Sheet'!D23)>1,"ERROR","OK"),"CHECK BROKEN") -> OK | E3: =IF(ISNUMBER('Balance Sheet'!E23),IF(ABS('Balance Sheet'!E23)>1,"ERROR","OK"),"CHECK BROKEN") -> OK | F3: =IF(ISNUMBER('Balance Sheet'!F23),IF(ABS('Balance Sheet'!F23)>1,"ERROR","OK"),"CHECK BROKEN") -> OK | G3: =IF(ISNUMBER('Balance Sheet'!G23),IF(ABS('Balance Sheet'!G23)>1,"ERROR","OK"),"CHECK BROKEN") -> OK | H3: =IF(ISNUMBER('Balance Sheet'!H23),IF(ABS('Balance Sheet'!H23)>1,"ERROR","OK"),"CHECK BROKEN") -> OK | I3: =IF(ISNUMBER('Balance Sheet'!I23),IF(ABS('Balance Sheet'!I23)>1,"ERROR","OK"),"CHECK BROKEN") -> OK | J3: =IF(ISNUMBER('Balance Sheet'!J23),IF(ABS('Balance Sheet'!J23)>1,"ERROR","OK"),"CHECK BROKEN") -> OK | K3: =IF(ISNUMBER('Balance Sheet'!K23),IF(ABS('Balance Sheet'!K23)>1,"ERROR","OK"),"CHECK BROKEN") -> OK | ... M3: =IF(ISNUMBER('Balance Sheet'!M23),IF(ABS('Balance Sheet'!M23)>1,"ERROR","OK"),"CHECK BROKEN") -> OK
A5: Assumptions
A7: Key Assumptions
A8: Revenue Growth (% Change) | E8: ='Income Statement'!E6/'Income Statement'!D6-1 -> 0.15762644 | F8: ='Income Statement'!F6/'Income Statement'!E6-1 -> 0.11228257 | G8: ='Income Statement'!G6/'Income Statement'!F6-1 -> 0.083718451 | H8: ='Income Statement'!H6/'Income Statement'!G6-1 -> 0.059231002 | I8: 0.1 | J8: 0.1 | K8: 0.1 | L8: 0.1 | M8: 0.1
A9: Cost of Goods Sold (% of Revenue) | D9: ='Income Statement'!D7/'Income Statement'!D6 -> 0.38255218 | E9: ='Income Statement'!E7/'Income Statement'!E6 -> 0.40651728 | F9: ='Income Statement'!F7/'Income Statement'!F6 -> 0.37399977 | G9: ='Income Statement'!G7/'Income Statement'!G6 -> 0.3699145 | H9: ='Income Statement'!H7/'Income Statement'!H6 -> 0.37613085 | I9: 0.42 | J9: 0.47 | K9: 0.5 | L9: 0.48 | M9: 0.42
A10: Salaries and Benefits (% of Revenue) | D10: ='Income Statement'!D10/'Income Statement'!D6 -> 0.25907046 | E10: ='Income Statement'!E10/'Income Statement'!E6 -> 0.19187711 | F10: ='Income Statement'!F10/'Income Statement'!F6 -> 0.18175035 | G10: ='Income Statement'!G10/'Income Statement'!G6 -> 0.16159785 | H10: ='Income Statement'!H10/'Income Statement'!H6 -> 0.16743825 | I10: 0.17 | J10: 0.17 | K10: 0.17 | L10: 0.17 | M10: 0.17
A11: Rent and Overhead ($000's) | D11: ='Income Statement'!D11 -> 10963 | E11: ='Income Statement'!E11 -> 10125 | F11: ='Income Statement'!F11 -> 10087 | G11: ='Income Statement'!G11 -> 11020 | H11: ='Income Statement'!H11 -> 11412 | I11: 15000 | J11: 15000 | K11: 15000 | L11: 15000 | M11: 15000
A12: Depreciation & Amortization (% of Opening PP&E) | D12: ='Income Statement'!D12/'Supporting Schedules'!D14 -> 0.39 | E12: ='Income Statement'!E12/'Supporting Schedules'!E14 -> 0.3989011 | F12: ='Income Statement'!F12/'Supporting Schedules'!F14 -> 0.40625738 | G12: ='Income Statement'!G12/'Supporting Schedules'!G14 -> 0.41210612 | H12: ='Income Statement'!H12/'Supporting Schedules'!H14 -> 0.41656952 | I12: 0.35 | J12: 0.35 | K12: 0.35 | L12: 0.35 | M12: 0.35
A13: Interest Expense (% of Average Debt) | D13: ='Income Statement'!D14/AVERAGE('Supporting Schedules'!D20,'Supporting Schedules'!D22) -> 0.05 | E13: ='Income Statement'!E14/AVERAGE('Supporting Schedules'!E20,'Supporting Schedules'!E22) -> 0.05 | F13: ='Income Statement'!F14/AVERAGE('Supporting Schedules'!F20,'Supporting Schedules'!F22) -> 0.0375 | G13: ='Income Statement'!G14/AVERAGE('Supporting Schedules'!G20,'Supporting Schedules'!G22) -> 0.05 | H13: ='Income Statement'!H14/AVERAGE('Supporting Schedules'!H20,'Supporting Schedules'!H22) -> 0.05 | I13: 0.1 | J13: 0.1 | K13: 0.1 | L13: 0.1 | M13: 0.1
A14: Interest Income (% of Opening Cash) | D14: =IF('Cash Flow Statement'!D22=0,0,-'Income Statement'!D13/'Cash Flow Statement'!D22) -> 0 | E14: =IF('Cash Flow Statement'!E22=0,0,-'Income Statement'!E13/'Cash Flow Statement'!E22) -> 0 | F14: =IF('Cash Flow Statement'!F22=0,0,-'Income Statement'!F13/'Cash Flow Statement'!F22) -> 0 | G14: =IF('Cash Flow Statement'!G22=0,0,-'Income Statement'!G13/'Cash Flow Statement'!G22) -> 0 | H14: =IF('Cash Flow Statement'!H22=0,0,-'Income Statement'!H13/'Cash Flow Statement'!H22) -> 0 | I14: 0.04 | J14: 0.04 | K14: 0.04 | L14: 0.04 | M14: 0.04
A15: Tax Rate (% of Earnings Before Tax) | D15: ='Income Statement'!D18/'Income Statement'!D16 -> 0.3116305 | E15: ='Income Statement'!E18/'Income Statement'!E16 -> 0.2917893 | F15: ='Income Statement'!F18/'Income Statement'!F16 -> 0.28699506 | G15: ='Income Statement'!G18/'Income Statement'!G16 -> 0.28994445 | H15: ='Income Statement'!H18/'Income Statement'!H16 -> 0.29122411 | I15: 0.28 | J15: 0.28 | K15: 0.28 | L15: 0.28 | M15: 0.28
A16: Accounts Receivable (Days) | D16: ='Balance Sheet'!D8/'Income Statement'!D6*365 -> 18.248748 | E16: ='Balance Sheet'!E8/'Income Statement'!E6*365 -> 18.249073 | F16: ='Balance Sheet'!F8/'Income Statement'!F6*365 -> 18.249305 | G16: ='Balance Sheet'!G8/'Income Statement'!G6*365 -> 18.249872 | H16: ='Balance Sheet'!H8/'Income Statement'!H6*365 -> 18.248547 | I16: 18 | J16: 18 | K16: 18 | L16: 18 | M16: 18
A17: Inventory (Days) | D17: ='Balance Sheet'!D9/'Income Statement'!D7*365 -> 73.003741 | E17: ='Balance Sheet'!E9/'Income Statement'!E7*365 -> 73.001521 | F17: ='Balance Sheet'!F9/'Income Statement'!F7*365 -> 73.002972 | G17: ='Balance Sheet'!G9/'Income Statement'!G7*365 -> 73.001386 | H17: ='Balance Sheet'!H9/'Income Statement'!H7*365 -> 73 | I17: 80 | J17: 90 | K17: 100 | L17: 100 | M17: 100
A18: Accounts Payable (Days) | D18: ='Balance Sheet'!D14/'Income Statement'!D7*365 -> 36.497194 | E18: ='Balance Sheet'!E14/'Income Statement'!E7*365 -> 36.496959 | F18: ='Balance Sheet'!F14/'Income Statement'!F7*365 -> 36.497771 | G18: ='Balance Sheet'!G14/'Income Statement'!G7*365 -> 36.504159 | H18: ='Balance Sheet'!H14/'Income Statement'!H7*365 -> 36.493564 | I18: 37 | J18: 37 | K18: 37 | L18: 37 | M18: 37
A19: Capital Expenditures ($000's) | D19: ='Cash Flow Statement'!D13 -> 15000 | E19: ='Cash Flow Statement'!E13 -> 15000 | F19: ='Cash Flow Statement'!F13 -> 15000 | G19: ='Cash Flow Statement'!G13 -> 15000 | H19: ='Cash Flow Statement'!H13 -> 15000 | I19: 15000 | J19: 15000 | K19: 15000 | L19: 15000 | M19: 15000
A20: Debt Issuance (Repayment) ($000's) | D20: ='Cash Flow Statement'!D17 -> 0 | E20: ='Cash Flow Statement'!E17 -> 0 | F20: ='Cash Flow Statement'!F17 -> -20000 | G20: ='Cash Flow Statement'!G17 -> 0 | H20: ='Cash Flow Statement'!H17 -> 0 | I20: 0 | J20: 0 | K20: -20000 | L20: 0 | M20: 0
A21: Equity Issued (Repaid) ($000's) | D21: ='Cash Flow Statement'!D18 -> 70000 | E21: ='Cash Flow Statement'!E18 -> 0 | F21: ='Cash Flow Statement'!F18 -> 0 | G21: ='Cash Flow Statement'!G18 -> 0 | H21: ='Cash Flow Statement'!H18 -> 0 | I21: 0 | J21: 0 | K21: 0 | L21: 0 | M21: 0
A22: Days in Period | D22: 365 | E22: 365 | F22: 365 | G22: 365 | H22: 365 | I22: 365 | J22: 365 | K22: 365 | L22: 365 | M22: 365
A24: Charts and Graphs
A26: Revenue | D26: ='Income Statement'!D6 -> 102007 | E26: ='Income Statement'!E6 -> 118086 | F26: ='Income Statement'!F6 -> 131345 | G26: ='Income Statement'!G6 -> 142341 | H26: ='Income Statement'!H6 -> 150772 | I26: ='Income Statement'!I6 -> 165849.2 | J26: ='Income Statement'!J6 -> 182434.12 | K26: ='Income Statement'!K6 -> 200677.53 | ... M26: ='Income Statement'!M6 -> 242819.81
A27: Gross Profit Margin (%) | D27: ='Income Statement'!D8/'Income Statement'!D6 -> 0.61744782 | E27: ='Income Statement'!E8/'Income Statement'!E6 -> 0.59348272 | F27: ='Income Statement'!F8/'Income Statement'!F6 -> 0.62600023 | G27: ='Income Statement'!G8/'Income Statement'!G6 -> 0.6300855 | H27: ='Income Statement'!H8/'Income Statement'!H6 -> 0.62386915 | I27: ='Income Statement'!I8/'Income Statement'!I6 -> 0.58 | J27: ='Income Statement'!J8/'Income Statement'!J6 -> 0.53 | K27: ='Income Statement'!K8/'Income Statement'!K6 -> 0.5 | ... M27: ='Income Statement'!M8/'Income Statement'!M6 -> 0.58
A29: Operating Cash Flow | D29: ='Cash Flow Statement'!D10 -> 12971 | E29: ='Cash Flow Statement'!E10 -> 28239 | F29: ='Cash Flow Statement'!F10 -> 37505 | G29: ='Cash Flow Statement'!G10 -> 42355 | H29: ='Cash Flow Statement'!H10 -> 43479 | I29: ='Cash Flow Statement'!I10 -> 40519.761 | J29: ='Cash Flow Statement'!J10 -> 37878.729 | K29: ='Cash Flow Statement'!K10 -> 39065.009 | ... M29: ='Cash Flow Statement'!M10 -> 70452.194
A30: Investing Cash Flow | D30: =-'Cash Flow Statement'!D14 -> -15000 | E30: =-'Cash Flow Statement'!E14 -> -15000 | F30: =-'Cash Flow Statement'!F14 -> -15000 | G30: =-'Cash Flow Statement'!G14 -> -15000 | H30: =-'Cash Flow Statement'!H14 -> -15000 | I30: =-'Cash Flow Statement'!I14 -> -15000 | J30: =-'Cash Flow Statement'!J14 -> -15000 | K30: =-'Cash Flow Statement'!K14 -> -15000 | ... M30: =-'Cash Flow Statement'!M14 -> -15000
A31: Financing Cash Flow | D31: ='Cash Flow Statement'!D19 -> 70000 | E31: ='Cash Flow Statement'!E19 -> 0 | F31: ='Cash Flow Statement'!F19 -> -20000 | G31: ='Cash Flow Statement'!G19 -> 0 | H31: ='Cash Flow Statement'!H19 -> 0 | I31: ='Cash Flow Statement'!I19 -> 0 | J31: ='Cash Flow Statement'!J19 -> 0 | K31: ='Cash Flow Statement'!K19 -> -20000 | ... M31: ='Cash Flow Statement'!M19 -> 0

Sheet Income Statement
D1: Historical Results | I1: Forecast Period
D2: 2021 | E2: =+D2+1 -> 2022 | F2: =+E2+1 -> 2023 | G2: =+F2+1 -> 2024 | H2: =+G2+1 -> 2025 | I2: =+H2+1 -> 2026 | J2: =+I2+1 -> 2027 | K2: =+J2+1 -> 2028 | L2: =+K2+1 -> 2029 | M2: =+L2+1 -> 2030
A4: Income Statement
A6: Revenue | D6: 102007 | E6: 118086 | F6: 131345 | G6: 142341 | H6: 150772 | I6: =H6*(1+Assumptions!I8) -> 165849.2 | J6: =I6*(1+Assumptions!J8) -> 182434.12 | K6: =J6*(1+Assumptions!K8) -> 200677.53 | L6: =K6*(1+Assumptions!L8) -> 220745.29 | M6: =L6*(1+Assumptions!M8) -> 242819.81
A7: Cost of Goods Sold (COGS) | D7: 39023 | E7: 48004 | F7: 49123 | G7: 52654 | H7: 56710 | I7: =I6*Assumptions!I9 -> 69656.664 | J7: =J6*Assumptions!J9 -> 85744.036 | K7: =K6*Assumptions!K9 -> 100338.77 | L7: =L6*Assumptions!L9 -> 105957.74 | M7: =M6*Assumptions!M9 -> 101984.32
A8: Gross Profit | D8: =D6-D7 -> 62984 | E8: =E6-E7 -> 70082 | F8: =F6-F7 -> 82222 | G8: =G6-G7 -> 89687 | H8: =H6-H7 -> 94062 | I8: =I6-I7 -> 96192.536 | J8: =J6-J7 -> 96690.084 | K8: =K6-K7 -> 100338.77 | ... M8: =M6-M7 -> 140835.49
A9: Expenses
A10: Salaries and Benefits | D10: 26427 | E10: 22658 | F10: 23872 | G10: 23002 | H10: 25245 | I10: =Assumptions!I10*I6 -> 28194.364 | J10: =Assumptions!J10*J6 -> 31013.8 | K10: =Assumptions!K10*K6 -> 34115.18 | L10: =Assumptions!L10*L6 -> 37526.698 | M10: =Assumptions!M10*M6 -> 41279.368
A11: Rent and Overhead | D11: 10963 | E11: 10125 | F11: 10087 | G11: 11020 | H11: 11412 | I11: =Assumptions!I11 -> 15000 | J11: =Assumptions!J11 -> 15000 | K11: =Assumptions!K11 -> 15000 | L11: =Assumptions!L11 -> 15000 | M11: =Assumptions!M11 -> 15000
A12: Depreciation & Amortization | D12: 19500 | E12: 18150 | F12: 17205 | G12: 16544 | H12: 16080 | I12: ='Cash Flow Statement'!I8 -> 13132.35 | J12: ='Cash Flow Statement'!J8 -> 13786.028 | K12: ='Cash Flow Statement'!K8 -> 14210.918 | L12: ='Cash Flow Statement'!L8 -> 14487.097 | M12: ='Cash Flow Statement'!M8 -> 14666.613
A13: Less: Interest Income | D13: 0 | E13: 0 | F13: 0 | G13: 0 | H13: 0 | I13: =-'Supporting Schedules'!I27 -> -5581.96 | J13: =-'Supporting Schedules'!J27 -> -6602.7504 | K13: =-'Supporting Schedules'!K27 -> -7517.8996 | L13: =-'Supporting Schedules'!L27 -> -7680.5 | M13: =-'Supporting Schedules'!M27 -> -9149.8866
A14: Interest Expense | D14: 2500 | E14: 2500 | F14: 1500 | G14: 1500 | H14: 1500 | I14: ='Supporting Schedules'!I23 -> 3000 | J14: ='Supporting Schedules'!J23 -> 3000 | K14: ='Supporting Schedules'!K23 -> 2000 | L14: ='Supporting Schedules'!L23 -> 1000 | M14: ='Supporting Schedules'!M23 -> 1000
A15: Total Expenses | D15: =SUM(D10:D14) -> 59390 | E15: =SUM(E10:E14) -> 53433 | F15: =SUM(F10:F14) -> 52664 | G15: =SUM(G10:G14) -> 52066 | H15: =SUM(H10:H14) -> 54237 | I15: =SUM(I10:I14) -> 53744.754 | J15: =SUM(J10:J14) -> 56197.077 | K15: =SUM(K10:K14) -> 57808.199 | ... M15: =SUM(M10:M14) -> 62796.095
A16: Earnings Before Tax | D16: =D8-D15 -> 3594 | E16: =E8-E15 -> 16649 | F16: =F8-F15 -> 29558 | G16: =G8-G15 -> 37621 | H16: =H8-H15 -> 39825 | I16: =I8-I15 -> 42447.782 | J16: =J8-J15 -> 40493.006 | K16: =K8-K15 -> 42530.567 | ... M16: =M8-M15 -> 78039.397
A18: Taxes | D18: 1120 | E18: 4858 | F18: 8483 | G18: 10908 | H18: 11598 | I18: =I16*Assumptions!I15 -> 11885.379 | J18: =J16*Assumptions!J15 -> 11338.042 | K18: =K16*Assumptions!K15 -> 11908.559 | L18: =L16*Assumptions!L15 -> 15247.191 | M18: =M16*Assumptions!M15 -> 21851.031
A19: Net Earnings | D19: =D16-D18 -> 2474 | E19: =E16-E18 -> 11791 | F19: =F16-F18 -> 21075 | G19: =G16-G18 -> 26713 | H19: =H16-H18 -> 28227 | I19: =I16-I18 -> 30562.403 | J19: =J16-J18 -> 29154.964 | K19: =K16-K18 -> 30622.008 | ... M19: =M16-M18 -> 56188.366

Sheet Balance Sheet
D1: Historical Results | I1: Forecast Period
D2: 2021 | E2: =+D2+1 -> 2022 | F2: =+E2+1 -> 2023 | G2: =+F2+1 -> 2024 | H2: =+G2+1 -> 2025 | I2: =+H2+1 -> 2026 | J2: =+I2+1 -> 2027 | K2: =+J2+1 -> 2028 | L2: =+K2+1 -> 2029 | M2: =+L2+1 -> 2030
A4: Balance Sheet
A6: Assets
A7: Cash | D7: 67971 | E7: 81210 | F7: 83715 | G7: 111070 | H7: 139549 | I7: ='Cash Flow Statement'!I23 -> 165068.76 | J7: ='Cash Flow Statement'!J23 -> 187947.49 | K7: ='Cash Flow Statement'!K23 -> 192012.5 | L7: ='Cash Flow Statement'!L23 -> 228747.17 | M7: ='Cash Flow Statement'!M23 -> 284199.36
A8: Accounts Receivable | D8: 5100 | E8: 5904 | F8: 6567 | G8: 7117 | H8: 7538 | I8: ='Income Statement'!I6*Assumptions!I16/Assumptions!I22 -> 8178.8647 | J8: ='Income Statement'!J6*Assumptions!J16/Assumptions!J22 -> 8996.7511 | K8: ='Income Statement'!K6*Assumptions!K16/Assumptions!K22 -> 9896.4262 | L8: ='Income Statement'!L6*Assumptions!L16/Assumptions!L22 -> 10886.069 | M8: ='Income Statement'!M6*Assumptions!M16/Assumptions!M22 -> 11974.676
A9: Inventory | D9: 7805 | E9: 9601 | F9: 9825 | G9: 10531 | H9: 11342 | I9: ='Income Statement'!I7*Assumptions!I17/Assumptions!I22 -> 15267.214 | J9: ='Income Statement'!J7*Assumptions!J17/Assumptions!J22 -> 21142.365 | K9: ='Income Statement'!K7*Assumptions!K17/Assumptions!K22 -> 27490.073 | L9: ='Income Statement'!L7*Assumptions!L17/Assumptions!L22 -> 29029.517 | M9: ='Income Statement'!M7*Assumptions!M17/Assumptions!M22 -> 27940.91
A10: Property & Equipment | D10: 45500 | E10: 42350 | F10: 40145 | G10: 38601 | H10: 37521 | I10: ='Supporting Schedules'!I17 -> 39388.65 | J10: ='Supporting Schedules'!J17 -> 40602.623 | K10: ='Supporting Schedules'!K17 -> 41391.705 | L10: ='Supporting Schedules'!L17 -> 41904.608 | M10: ='Supporting Schedules'!M17 -> 42237.995
A11: Total Assets | D11: =SUM(D7:D10) -> 126376 | E11: =SUM(E7:E10) -> 139065 | F11: =SUM(F7:F10) -> 140252 | G11: =SUM(G7:G10) -> 167319 | H11: =SUM(H7:H10) -> 195950 | I11: =SUM(I7:I10) -> 227903.49 | J11: =SUM(J7:J10) -> 258689.23 | K11: =SUM(K7:K10) -> 270790.7 | ... M11: =SUM(M7:M10) -> 366352.94
A13: Liabilities
A14: Accounts Payable | D14: 3902 | E14: 4800 | F14: 4912 | G14: 5266 | H14: 5670 | I14: ='Income Statement'!I7*Assumptions!I18/Assumptions!I22 -> 7061.0865 | J14: ='Income Statement'!J7*Assumptions!J18/Assumptions!J22 -> 8691.8612 | K14: ='Income Statement'!K7*Assumptions!K18/Assumptions!K22 -> 10171.327 | L14: ='Income Statement'!L7*Assumptions!L18/Assumptions!L22 -> 10740.921 | M14: ='Income Statement'!M7*Assumptions!M18/Assumptions!M22 -> 10338.137
A15: Debt | D15: 50000 | E15: 50000 | F15: 30000 | G15: 30000 | H15: 30000 | I15: ='Supporting Schedules'!I22 -> 30000 | J15: ='Supporting Schedules'!J22 -> 30000 | K15: ='Supporting Schedules'!K22 -> 10000 | L15: ='Supporting Schedules'!L22 -> 10000 | M15: ='Supporting Schedules'!M22 -> 10000
A16: Total Liabilities | D16: =SUM(D14:D15) -> 53902 | E16: =SUM(E14:E15) -> 54800 | F16: =SUM(F14:F15) -> 34912 | G16: =SUM(G14:G15) -> 35266 | H16: =SUM(H14:H15) -> 35670 | I16: =SUM(I14:I15) -> 37061.086 | J16: =SUM(J14:J15) -> 38691.861 | K16: =SUM(K14:K15) -> 20171.327 | ... M16: =SUM(M14:M15) -> 20338.137
A17: Shareholder's Equity
A18: Equity Capital | D18: 70000 | E18: 70000 | F18: 70000 | G18: 70000 | H18: 70000 | I18: =H18+'Cash Flow Statement'!I18 -> 70000 | J18: =I18+'Cash Flow Statement'!J18 -> 70000 | K18: =J18+'Cash Flow Statement'!K18 -> 70000 | L18: =K18+'Cash Flow Statement'!L18 -> 70000 | M18: =L18+'Cash Flow Statement'!M18 -> 70000
A19: Retained Earnings | D19: 2474 | E19: 14265 | F19: 35340 | G19: 62053 | H19: 90280 | I19: =H19+'Income Statement'!I19 -> 120842.4 | J19: =I19+'Income Statement'!J19 -> 149997.37 | K19: =J19+'Income Statement'!K19 -> 180619.38 | L19: =K19+'Income Statement'!L19 -> 219826.44 | M19: =L19+'Income Statement'!M19 -> 276014.8
A20: Shareholder's Equity | D20: =SUM(D18:D19) -> 72474 | E20: =SUM(E18:E19) -> 84265 | F20: =SUM(F18:F19) -> 105340 | G20: =SUM(G18:G19) -> 132053 | H20: =SUM(H18:H19) -> 160280 | I20: =SUM(I18:I19) -> 190842.4 | J20: =SUM(J18:J19) -> 219997.37 | K20: =SUM(K18:K19) -> 250619.38 | ... M20: =SUM(M18:M19) -> 346014.8
A21: Total Liabilities & Shareholder's Equity | D21: =D16+D20 -> 126376 | E21: =E16+E20 -> 139065 | F21: =F16+F20 -> 140252 | G21: =G16+G20 -> 167319 | H21: =H16+H20 -> 195950 | I21: =I16+I20 -> 227903.49 | J21: =J16+J20 -> 258689.23 | K21: =K16+K20 -> 270790.7 | ... M21: =M16+M20 -> 366352.94
A23: Check | D23: =D21-D11 -> 0 | E23: =E21-E11 -> 0 | F23: =F21-F11 -> 0 | G23: =G21-G11 -> 0 | H23: =H21-H11 -> 0 | I23: =I21-I11 -> 0 | J23: =J21-J11 -> 0 | K23: =K21-K11 -> 0 | ... M23: =M21-M11 -> 0

Sheet Cash Flow Statement
D1: Historical Results | I1: Forecast Period
D2: 2021 | E2: =+D2+1 -> 2022 | F2: =+E2+1 -> 2023 | G2: =+F2+1 -> 2024 | H2: =+G2+1 -> 2025 | I2: =+H2+1 -> 2026 | J2: =+I2+1 -> 2027 | K2: =+J2+1 -> 2028 | L2: =+K2+1 -> 2029 | M2: =+L2+1 -> 2030
A4: Cash Flow Statement
A6: Operating Cash Flow
A7: Net Earnings | D7: 2474 | E7: 11791 | F7: 21075 | G7: 26713 | H7: 28227 | I7: ='Income Statement'!I19 -> 30562.403 | J7: ='Income Statement'!J19 -> 29154.964 | K7: ='Income Statement'!K19 -> 30622.008 | L7: ='Income Statement'!L19 -> 39207.062 | M7: ='Income Statement'!M19 -> 56188.366
A8: Plus: Depreciation & Amortization | D8: 19500 | E8: 18150 | F8: 17205 | G8: 16544 | H8: 16080 | I8: ='Supporting Schedules'!I16 -> 13132.35 | J8: ='Supporting Schedules'!J16 -> 13786.028 | K8: ='Supporting Schedules'!K16 -> 14210.918 | L8: ='Supporting Schedules'!L16 -> 14487.097 | M8: ='Supporting Schedules'!M16 -> 14666.613
A9: Less: Changes in Working Capital | D9: 9003 | E9: 1702 | F9: 775 | G9: 902 | H9: 828 | I9: ='Supporting Schedules'!I11 -> 3174.9922 | J9: ='Supporting Schedules'!J11 -> 5062.2628 | K9: ='Supporting Schedules'!K11 -> 5767.9171 | L9: ='Supporting Schedules'!L11 -> 1959.4924 | M9: ='Supporting Schedules'!M11 -> 402.78455
A10: Cash from Operations | D10: =D7+D8-D9 -> 12971 | E10: =E7+E8-E9 -> 28239 | F10: =F7+F8-F9 -> 37505 | G10: =G7+G8-G9 -> 42355 | H10: =H7+H8-H9 -> 43479 | I10: =I7+I8-I9 -> 40519.761 | J10: =J7+J8-J9 -> 37878.729 | K10: =K7+K8-K9 -> 39065.009 | ... M10: =M7+M8-M9 -> 70452.194
A12: Investing Cash Flow
A13: Investments in Property & Equipment | D13: 15000 | E13: 15000 | F13: 15000 | G13: 15000 | H13: 15000 | I13: ='Supporting Schedules'!I15 -> 15000 | J13: ='Supporting Schedules'!J15 -> 15000 | K13: ='Supporting Schedules'!K15 -> 15000 | L13: ='Supporting Schedules'!L15 -> 15000 | M13: ='Supporting Schedules'!M15 -> 15000
A14: Cash from Investing | D14: =SUM(D13) -> 15000 | E14: =SUM(E13) -> 15000 | F14: =SUM(F13) -> 15000 | G14: =SUM(G13) -> 15000 | H14: =SUM(H13) -> 15000 | I14: =SUM(I13) -> 15000 | J14: =SUM(J13) -> 15000 | K14: =SUM(K13) -> 15000 | ... M14: =SUM(M13) -> 15000
A16: Financing Cash Flow
A17: Issuance (repayment) of debt | D17: 0 | E17: 0 | F17: -20000 | G17: 0 | H17: 0 | I17: ='Supporting Schedules'!I21 -> 0 | J17: ='Supporting Schedules'!J21 -> 0 | K17: ='Supporting Schedules'!K21 -> -20000 | L17: ='Supporting Schedules'!L21 -> 0 | M17: ='Supporting Schedules'!M21 -> 0
A18: Issuance (repayment) of equity | D18: 70000 | E18: 0 | F18: 0 | G18: 0 | H18: 0 | I18: =Assumptions!I21 -> 0 | J18: =Assumptions!J21 -> 0 | K18: =Assumptions!K21 -> 0 | L18: =Assumptions!L21 -> 0 | M18: =Assumptions!M21 -> 0
A19: Cash from Financing | D19: =SUM(D17:D18) -> 70000 | E19: =SUM(E17:E18) -> 0 | F19: =SUM(F17:F18) -> -20000 | G19: =SUM(G17:G18) -> 0 | H19: =SUM(H17:H18) -> 0 | I19: =SUM(I17:I18) -> 0 | J19: =SUM(J17:J18) -> 0 | K19: =SUM(K17:K18) -> -20000 | ... M19: =SUM(M17:M18) -> 0
A21: Net Increase (decrease) in Cash | D21: =D10-D14+D19 -> 67971 | E21: =E10-E14+E19 -> 13239 | F21: =F10-F14+F19 -> 2505 | G21: =G10-G14+G19 -> 27355 | H21: =H10-H14+H19 -> 28479 | I21: =I10-I14+I19 -> 25519.761 | J21: =J10-J14+J19 -> 22878.729 | K21: =K10-K14+K19 -> 4065.0092 | ... M21: =M10-M14+M19 -> 55452.194
A22: Opening Cash Balance | D22: 0 | E22: =D23 -> 67971 | F22: =E23 -> 81210 | G22: =F23 -> 83715 | H22: =G23 -> 111070 | I22: =H23 -> 139549 | J22: =I23 -> 165068.76 | K22: =J23 -> 187947.49 | L22: =K23 -> 192012.5 | M22: =L23 -> 228747.17
A23: Closing Cash Balance | D23: =SUM(D21:D22) -> 67971 | E23: =SUM(E21:E22) -> 81210 | F23: =SUM(F21:F22) -> 83715 | G23: =SUM(G21:G22) -> 111070 | H23: =SUM(H21:H22) -> 139549 | I23: =SUM(I21:I22) -> 165068.76 | J23: =SUM(J21:J22) -> 187947.49 | K23: =SUM(K21:K22) -> 192012.5 | ... M23: =SUM(M21:M22) -> 284199.36

Sheet Supporting Schedules
D1: Historical Results | I1: Forecast Period
D2: 2021 | E2: =+D2+1 -> 2022 | F2: =+E2+1 -> 2023 | G2: =+F2+1 -> 2024 | H2: =+G2+1 -> 2025 | I2: =+H2+1 -> 2026 | J2: =+I2+1 -> 2027 | K2: =+J2+1 -> 2028 | L2: =+K2+1 -> 2029 | M2: =+L2+1 -> 2030
A4: Supporting Schedules
A6: Working Capital Schedule
A7: Accounts Receivable | D7: ='Balance Sheet'!D8 -> 5100 | E7: ='Balance Sheet'!E8 -> 5904 | F7: ='Balance Sheet'!F8 -> 6567 | G7: ='Balance Sheet'!G8 -> 7117 | H7: ='Balance Sheet'!H8 -> 7538 | I7: ='Balance Sheet'!I8 -> 8178.8647 | J7: ='Balance Sheet'!J8 -> 8996.7511 | K7: ='Balance Sheet'!K8 -> 9896.4262 | ... M7: ='Balance Sheet'!M8 -> 11974.676
A8: Inventory | D8: ='Balance Sheet'!D9 -> 7805 | E8: ='Balance Sheet'!E9 -> 9601 | F8: ='Balance Sheet'!F9 -> 9825 | G8: ='Balance Sheet'!G9 -> 10531 | H8: ='Balance Sheet'!H9 -> 11342 | I8: ='Balance Sheet'!I9 -> 15267.214 | J8: ='Balance Sheet'!J9 -> 21142.365 | K8: ='Balance Sheet'!K9 -> 27490.073 | ... M8: ='Balance Sheet'!M9 -> 27940.91
A9: Accounts Payable | D9: ='Balance Sheet'!D14 -> 3902 | E9: ='Balance Sheet'!E14 -> 4800 | F9: ='Balance Sheet'!F14 -> 4912 | G9: ='Balance Sheet'!G14 -> 5266 | H9: ='Balance Sheet'!H14 -> 5670 | I9: ='Balance Sheet'!I14 -> 7061.0865 | J9: ='Balance Sheet'!J14 -> 8691.8612 | K9: ='Balance Sheet'!K14 -> 10171.327 | ... M9: ='Balance Sheet'!M14 -> 10338.137
A10: Net Working Capital (NWC) | D10: =D7+D8-D9 -> 9003 | E10: =E7+E8-E9 -> 10705 | F10: =F7+F8-F9 -> 11480 | G10: =G7+G8-G9 -> 12382 | H10: =H7+H8-H9 -> 13210 | I10: =I7+I8-I9 -> 16384.992 | J10: =J7+J8-J9 -> 21447.255 | K10: =K7+K8-K9 -> 27215.172 | ... M10: =M7+M8-M9 -> 29577.449
A11: Change in NWC | D11: =IF(C10="","n/a",D10-C10) -> n/a | E11: =E10-D10 -> 1702 | F11: =F10-E10 -> 775 | G11: =G10-F10 -> 902 | H11: =H10-G10 -> 828 | I11: =I10-H10 -> 3174.9922 | J11: =J10-I10 -> 5062.2628 | K11: =K10-J10 -> 5767.9171 | L11: =L10-K10 -> 1959.4924 | M11: =M10-L10 -> 402.78455
A13: Depreciation Schedule
A14: PPE Opening | D14: 50000 | E14: =D17 -> 45500 | F14: =E17 -> 42350 | G14: =F17 -> 40145 | H14: =G17 -> 38601 | I14: =H17 -> 37521 | J14: =I17 -> 39388.65 | K14: =J17 -> 40602.623 | L14: =K17 -> 41391.705 | M14: =L17 -> 41904.608
A15: Plus Capex | D15: ='Cash Flow Statement'!D13 -> 15000 | E15: ='Cash Flow Statement'!E13 -> 15000 | F15: ='Cash Flow Statement'!F13 -> 15000 | G15: ='Cash Flow Statement'!G13 -> 15000 | H15: ='Cash Flow Statement'!H13 -> 15000 | I15: =Assumptions!I19 -> 15000 | J15: =Assumptions!J19 -> 15000 | K15: =Assumptions!K19 -> 15000 | L15: =Assumptions!L19 -> 15000 | M15: =Assumptions!M19 -> 15000
A16: Less Depreciation | D16: ='Cash Flow Statement'!D8 -> 19500 | E16: ='Cash Flow Statement'!E8 -> 18150 | F16: ='Cash Flow Statement'!F8 -> 17205 | G16: ='Cash Flow Statement'!G8 -> 16544 | H16: ='Cash Flow Statement'!H8 -> 16080 | I16: =I14*Assumptions!I12 -> 13132.35 | J16: =J14*Assumptions!J12 -> 13786.028 | K16: =K14*Assumptions!K12 -> 14210.918 | L16: =L14*Assumptions!L12 -> 14487.097 | M16: =M14*Assumptions!M12 -> 14666.613
A17: PPE Closing | D17: =D14+D15-D16 -> 45500 | E17: =E14+E15-E16 -> 42350 | F17: =F14+F15-F16 -> 40145 | G17: =G14+G15-G16 -> 38601 | H17: =H14+H15-H16 -> 37521 | I17: =I14+I15-I16 -> 39388.65 | J17: =J14+J15-J16 -> 40602.623 | K17: =K14+K15-K16 -> 41391.705 | ... M17: =M14+M15-M16 -> 42237.995
A19: Debt & Interest Schedule
A20: Debt Opening | D20: 50000 | E20: =D22 -> 50000 | F20: =E22 -> 50000 | G20: =F22 -> 30000 | H20: =G22 -> 30000 | I20: =H22 -> 30000 | J20: =I22 -> 30000 | K20: =J22 -> 30000 | L20: =K22 -> 10000 | M20: =L22 -> 10000
A21: Issuance (repayment) | D21: ='Cash Flow Statement'!D17 -> 0 | E21: ='Cash Flow Statement'!E17 -> 0 | F21: ='Cash Flow Statement'!F17 -> -20000 | G21: ='Cash Flow Statement'!G17 -> 0 | H21: ='Cash Flow Statement'!H17 -> 0 | I21: =Assumptions!I20 -> 0 | J21: =Assumptions!J20 -> 0 | K21: =Assumptions!K20 -> -20000 | L21: =Assumptions!L20 -> 0 | M21: =Assumptions!M20 -> 0
A22: Debt Closing | D22: =D20+D21 -> 50000 | E22: =E20+E21 -> 50000 | F22: =F20+F21 -> 30000 | G22: =G20+G21 -> 30000 | H22: =H20+H21 -> 30000 | I22: =I20+I21 -> 30000 | J22: =J20+J21 -> 30000 | K22: =K20+K21 -> 10000 | ... M22: =M20+M21 -> 10000
A23: Interest Expense | D23: ='Income Statement'!D14 -> 2500 | E23: ='Income Statement'!E14 -> 2500 | F23: ='Income Statement'!F14 -> 1500 | G23: ='Income Statement'!G14 -> 1500 | H23: ='Income Statement'!H14 -> 1500 | I23: =AVERAGE(I20,I22)*Assumptions!I13 -> 3000 | J23: =AVERAGE(J20,J22)*Assumptions!J13 -> 3000 | K23: =AVERAGE(K20,K22)*Assumptions!K13 -> 2000 | L23: =AVERAGE(L20,L22)*Assumptions!L13 -> 1000 | M23: =AVERAGE(M20,M22)*Assumptions!M13 -> 1000
A25: Cash & Interest Income Schedule
A26: Cash Opening | D26: ='Cash Flow Statement'!D22 -> 0 | E26: ='Cash Flow Statement'!E22 -> 67971 | F26: ='Cash Flow Statement'!F22 -> 81210 | G26: ='Cash Flow Statement'!G22 -> 83715 | H26: ='Cash Flow Statement'!H22 -> 111070 | I26: ='Cash Flow Statement'!I22 -> 139549 | J26: ='Cash Flow Statement'!J22 -> 165068.76 | K26: ='Cash Flow Statement'!K22 -> 187947.49 | ... M26: ='Cash Flow Statement'!M22 -> 228747.17
A27: Interest Income | D27: =-'Income Statement'!D13 -> 0 | E27: =-'Income Statement'!E13 -> 0 | F27: =-'Income Statement'!F13 -> 0 | G27: =-'Income Statement'!G13 -> 0 | H27: =-'Income Statement'!H13 -> 0 | I27: =I26*Assumptions!I14 -> 5581.96 | J27: =J26*Assumptions!J14 -> 6602.7504 | K27: =K26*Assumptions!K14 -> 7517.8996 | L27: =L26*Assumptions!L14 -> 7680.5 | M27: =M26*Assumptions!M14 -> 9149.8866

Sheet Summary
A1: Executive Summary
A2: 5-Year Forecast Overview (2026-2030)
A4: Key Metrics
A5: Metric | B5: 2025 (Last Actual) | C5: 2030 (Forecast) | D5: Change
A6: Revenue ($000's) | B6: ='Income Statement'!H6 -> 150772 | C6: ='Income Statement'!M6 -> 242819.81 | D6: =C6/B6-1 -> 0.61051
A7: Revenue CAGR (2025-2030, 5 yrs) | C7: =(C6/B6)^(1/5)-1 -> 0.1
A8: Net Earnings ($000's) | B8: ='Income Statement'!H19 -> 28227 | C8: ='Income Statement'!M19 -> 56188.366 | D8: =C8/B8-1 -> 0.99058937
A9: Gross Profit Margin | B9: =Assumptions!H27 -> 0.62386915 | C9: =Assumptions!M27 -> 0.58 | D9: =C9-B9 -> -0.043869153
A10: Ending Cash ($000's) | B10: ='Cash Flow Statement'!H23 -> 139549 | C10: ='Cash Flow Statement'!M23 -> 284199.36 | D10: =C10/B10-1 -> 1.036556
A11: Total Debt ($000's) | B11: ='Balance Sheet'!H15 -> 30000 | C11: ='Balance Sheet'!M15 -> 10000 | D11: =C11/B11-1 -> -0.66666667
A12: Total Assets ($000's) | B12: ='Balance Sheet'!H11 -> 195950 | C12: ='Balance Sheet'!M11 -> 366352.94 | D12: =C12/B12-1 -> 0.8696246
A13: Balance Sheet Check (should be 0) | B13: {=IF(COUNT('Balance Sheet'!D23:M23)<10,"CHECK BROKEN",SUMPRODUCT(ABS('Balance Sheet'!D23:M23)))} -> 0
A15: Key Takeaways
A16: ="• Revenue grows steadily across the forecast, at roughly a "&TEXT(C7,"0%")&" annual rate." -> • Revenue grows steadily across the forecast, at roughly a 10% annual rate.
A17: ="• Net earnings grow "&TEXT(D8,"0%")&" over the period, "&IF(D9>=0,"aided by expanding margins.","even as gross margin compresses slightly — worth a closer look.") -> • Net earnings grow 99% over the period, even as gross margin compresses slightly — worth a closer look.
A18: • The balance sheet strengthens over time: debt is paid down while cash builds up.
A19: {=IF(AND(COUNT('Balance Sheet'!D23:M23)=10,SUMPRODUCT(ABS('Balance Sheet'!D23:M23))<=1),"• The model ties out cleanly — Assets equal Liabilities + Equity in every year.","• WARNING: the balance sheet does not tie out in every year — see the check row.")} -> • The model ties out cleanly — Assets equal Liabilities + Equity in every year.
